[
    {
        "type": "message",
        "subtype": "channel_join",
        "ts": "1461827234.000102",
        "user": "U14E54P0R",
        "text": "<@U14E54P0R> has joined the channel"
    },
    {
        "type": "message",
        "subtype": "channel_join",
        "ts": "1461828679.000103",
        "user": "U14DWNVNJ",
        "text": "<@U14DWNVNJ> has joined the channel"
    },
    {
        "type": "message",
        "subtype": "channel_join",
        "ts": "1461843557.000104",
        "user": "U14FXL2DB",
        "text": "<@U14FXL2DB> has joined the channel"
    },
    {
        "type": "message",
        "subtype": "channel_join",
        "ts": "1461848284.000105",
        "user": "U14GG4E69",
        "text": "<@U14GG4E69> has joined the channel"
    },
    {
        "type": "message",
        "subtype": "channel_join",
        "ts": "1461868133.000106",
        "user": "U14L7977T",
        "text": "<@U14L7977T> has joined the channel"
    },
    {
        "type": "message",
        "subtype": "channel_join",
        "ts": "1461869988.000107",
        "user": "U14L5TKNJ",
        "text": "<@U14L5TKNJ> has joined the channel"
    }
]