[
    {
        "type": "message",
        "subtype": "channel_join",
        "ts": "1479632794.002143",
        "user": "U34RWCDS7",
        "text": "<@U34RWCDS7> has joined the channel"
    },
    {
        "type": "message",
        "text": "<@U2XDMN67J>  привет, да проходил. Воронцова очень уважаю, но курс очень сырой. ну прямо оооочень. не рекомендую",
        "user": "U24FQ67C7",
        "ts": "1479646059.002144",
        "team": "T040HKJE3",
        "user_team": "T040HKJE3",
        "source_team": "T040HKJE3",
        "user_profile": {
            "avatar_hash": "02255b2bc5c5",
            "image_72": "https:\/\/avatars.slack-edge.com\/2016-09-12\/78852470807_02255b2bc5c57ba7c529_72.jpg",
            "first_name": "Semen",
            "real_name": "Semen Kosyachenko",
            "display_name": "semen.kosyachenko",
            "team": "T040HKJE3",
            "name": "semen.kosyachenko",
            "is_restricted": false,
            "is_ultra_restricted": false
        },
        "reactions": [
            {
                "name": "heavy_plus_sign",
                "users": [
                    "U1UNFRQ1K"
                ],
                "count": 1
            }
        ]
    },
    {
        "type": "message",
        "subtype": "channel_join",
        "ts": "1479664476.002145",
        "user": "U34TH9KHR",
        "text": "<@U34TH9KHR> has joined the channel"
    },
    {
        "type": "message",
        "subtype": "channel_join",
        "ts": "1479676172.002146",
        "user": "U34ADCQ7K",
        "text": "<@U34ADCQ7K> has joined the channel"
    },
    {
        "type": "message",
        "text": "<https:\/\/github.com\/Developer-Y\/cs-video-courses\/blob\/master\/README.md> ",
        "user": "U14BPHDK6",
        "ts": "1479677128.002147",
        "team": "T040HKJE3",
        "user_team": "T040HKJE3",
        "source_team": "T040HKJE3",
        "user_profile": {
            "avatar_hash": "45d25e4e33d6",
            "image_72": "https:\/\/avatars.slack-edge.com\/2017-12-07\/283925328566_45d25e4e33d6da7c6d8b_72.png",
            "first_name": "Katya",
            "real_name": "Katya Demidova",
            "display_name": "katya",
            "team": "T040HKJE3",
            "name": "katya",
            "is_restricted": false,
            "is_ultra_restricted": false
        },
        "edited": {
            "user": "U14BPHDK6",
            "ts": "1479677138.000000"
        },
        "attachments": [
            {
                "service_name": "GitHub",
                "title": "Developer-Y\/cs-video-courses",
                "title_link": "https:\/\/github.com\/Developer-Y\/cs-video-courses\/blob\/master\/README.md",
                "text": "cs-video-courses - List of Computer Science courses with video lectures.",
                "fallback": "GitHub: Developer-Y\/cs-video-courses",
                "thumb_url": "https:\/\/avatars3.githubusercontent.com\/u\/22699926?v=3&s=400",
                "from_url": "https:\/\/github.com\/Developer-Y\/cs-video-courses\/blob\/master\/README.md",
                "thumb_width": 420,
                "thumb_height": 420,
                "service_icon": "https:\/\/github.com\/apple-touch-icon.png",
                "id": 1
            }
        ],
        "reactions": [
            {
                "name": "+1",
                "users": [
                    "U0UG04H3M",
                    "U1BMURR5G",
                    "U0AS1QEJF",
                    "U2N853RGF",
                    "U1CMPEWPQ",
                    "U041LH06L",
                    "U1CF95PP1",
                    "U1Z40FGQ6"
                ],
                "count": 8
            },
            {
                "name": "heavy_plus_sign",
                "users": [
                    "U2F68DB26",
                    "U2N853RGF",
                    "U1Z40FGQ6"
                ],
                "count": 3
            }
        ]
    },
    {
        "type": "message",
        "subtype": "pinned_item",
        "text": "<@U19HATM25> pinned a message to this channel.",
        "user": "U19HATM25",
        "item_type": "C",
        "attachments": [
            {
                "fallback": "[November 20th, 2016 1:25 PM] katya: <https:\/\/github.com\/Developer-Y\/cs-video-courses\/blob\/master\/README.md> ",
                "ts": "1479677128.002147",
                "author_id": "U14BPHDK6",
                "author_subname": "Katya Demidova",
                "channel_id": "C04DP7BUY",
                "channel_name": "edu_courses",
                "is_msg_unfurl": true,
                "text": "<https:\/\/github.com\/Developer-Y\/cs-video-courses\/blob\/master\/README.md> ",
                "author_name": "Katya Demidova",
                "author_link": "https:\/\/opendatascience.slack.com\/team\/U14BPHDK6",
                "author_icon": "https:\/\/avatars.slack-edge.com\/2017-12-07\/283925328566_45d25e4e33d6da7c6d8b_48.png",
                "mrkdwn_in": [
                    "text"
                ],
                "from_hidden_wksp": false
            }
        ],
        "ts": "1479687735.002150"
    }
]