[
    {
        "client_msg_id": "1e82ab5f-d32a-4b18-96df-83baa85e62e5",
        "type": "message",
        "text": "Да... Кажется, придется вслепую стрелять в ВК сообщениями)",
        "user": "U9QCAKDU0",
        "ts": "1548058013.398400",
        "team": "T040HKJE3",
        "user_team": "T040HKJE3",
        "source_team": "T040HKJE3",
        "user_profile": {
            "avatar_hash": "g5ea39d5480d",
            "image_72": "https:\/\/secure.gravatar.com\/avatar\/5ea39d5480de8f77cc5e1a3cb5bbc41a.jpg?s=72&d=https%3A%2F%2Fa.slack-edge.com%2Fdf10d%2Fimg%2Favatars%2Fava_0018-72.png",
            "first_name": "",
            "real_name": "1902A",
            "display_name": "",
            "team": "T040HKJE3",
            "name": "1902grand",
            "is_restricted": false,
            "is_ultra_restricted": false
        },
        "thread_ts": "1548053654.397300",
        "parent_user_id": "U9QCAKDU0"
    },
    {
        "client_msg_id": "B36B28AC-BFDF-49FB-B8FD-EDD8CC0EF354",
        "type": "message",
        "text": "Мб спросить тут? <#C2XEW8C4B|edu_shad_exams> ",
        "user": "U50EVF538",
        "ts": "1548058687.400300",
        "team": "T040HKJE3",
        "user_team": "T040HKJE3",
        "source_team": "T040HKJE3",
        "user_profile": {
            "avatar_hash": "81354e7d3e9e",
            "image_72": "https:\/\/avatars.slack-edge.com\/2017-06-27\/204725676311_81354e7d3e9e7b4af4d0_72.png",
            "first_name": "Stasian",
            "real_name": "Stasian Prikhodko",
            "display_name": "stasian",
            "team": "T040HKJE3",
            "name": "stasian",
            "is_restricted": false,
            "is_ultra_restricted": false
        },
        "thread_ts": "1548053654.397300",
        "parent_user_id": "U9QCAKDU0"
    },
    {
        "client_msg_id": "8c5c5122-a570-40ac-aa06-1ed183aead39",
        "type": "message",
        "text": "<@U50EVF538>\nО, спасибо. Не знал об этой ветке. Тут тогда подчищу оффтоп",
        "user": "U9QCAKDU0",
        "ts": "1548058929.400600",
        "team": "T040HKJE3",
        "user_team": "T040HKJE3",
        "source_team": "T040HKJE3",
        "user_profile": {
            "avatar_hash": "g5ea39d5480d",
            "image_72": "https:\/\/secure.gravatar.com\/avatar\/5ea39d5480de8f77cc5e1a3cb5bbc41a.jpg?s=72&d=https%3A%2F%2Fa.slack-edge.com%2Fdf10d%2Fimg%2Favatars%2Fava_0018-72.png",
            "first_name": "",
            "real_name": "1902A",
            "display_name": "",
            "team": "T040HKJE3",
            "name": "1902grand",
            "is_restricted": false,
            "is_ultra_restricted": false
        },
        "edited": {
            "user": "U9QCAKDU0",
            "ts": "1548058982.000000"
        },
        "thread_ts": "1548053654.397300",
        "parent_user_id": "U9QCAKDU0"
    },
    {
        "client_msg_id": "1b11e885-abdf-41af-a4d3-9d5444f53a59",
        "type": "message",
        "text": "Очень рекламные по сути курсы, очень долго рассказывают, как много может Гугл Клауд, и очень мало реально показывают. Польза в том, что если ты этого клауда никогда еще не видел, то можно бесплатно пощупать панель управления и посмотреть простые образцы проектов, которые точно работают. Все ноутбуки еще и на гитхабе есть, потом можно освежить в памяти. Личные деньги я бы на это не тратил, по промо или за счет работодателя, которому срочно надо на GCP начать, пойдет для начала.",
        "user": "UENSFU56C",
        "ts": "1548060667.401200",
        "team": "T040HKJE3",
        "user_team": "T040HKJE3",
        "source_team": "T040HKJE3",
        "user_profile": {
            "avatar_hash": "3307a3d6577b",
            "image_72": "https:\/\/avatars.slack-edge.com\/2019-04-01\/596642935671_3307a3d6577b87c6b594_72.jpg",
            "first_name": "Mikalai",
            "real_name": "Mikalai Rahachou",
            "display_name": "mickolka",
            "team": "T040HKJE3",
            "name": "mikalai.rahachou",
            "is_restricted": false,
            "is_ultra_restricted": false
        },
        "thread_ts": "1547984390.389100",
        "parent_user_id": "U4ZRFG1V0"
    },
    {
        "client_msg_id": "471af741-1c51-4131-b872-472b6bc95ab2",
        "type": "message",
        "text": "Коллеги, а как бы вы оценили количество часов, которые абстрактному программисту, пусть будет с математическим образованием, понадобится для того, чтобы уверенно овладеть актуальными методами DS\/ML. Понимаю что вопрос сложно конкретизировать, в том числе в части  “до какого именно уровня овладеть“. Если будут предложения о том, как его (вопрос) уточнить, буду благодарен. Пока, скажем, до уровня: способности самостоятельно вести DS\/ML проекты, или приносить пользу в команде.\nРечь, может идти, например, о каком нибудь разумном curriculum из этого списка ответов.",
        "user": "U48SBCYKX",
        "ts": "1548073817.409300",
        "team": "T040HKJE3",
        "user_team": "T040HKJE3",
        "source_team": "T040HKJE3",
        "user_profile": {
            "avatar_hash": "175d7cc768d0",
            "image_72": "https:\/\/avatars.slack-edge.com\/2017-08-24\/232430990807_175d7cc768d09d76d66a_72.jpg",
            "first_name": "Yury",
            "real_name": "Yury Zelensky",
            "display_name": "y.zelensky",
            "team": "T040HKJE3",
            "name": "y.zelensky",
            "is_restricted": false,
            "is_ultra_restricted": false
        },
        "thread_ts": "1548073817.409300",
        "reply_count": 33,
        "reply_users_count": 10,
        "latest_reply": "1548763957.634700",
        "reply_users": [
            "U48SBCYKX",
            "U48B3EN87",
            "U4ZRFG1V0",
            "U1CF22N7J",
            "U44J8KC13",
            "U6XP4JL49",
            "U35B82XT6",
            "U0H8RU34N",
            "UDTFQJN1M",
            "UA74839JP"
        ],
        "replies": [
            {
                "user": "U48SBCYKX",
                "ts": "1548073947.409600"
            },
            {
                "user": "U48B3EN87",
                "ts": "1548074179.409800"
            },
            {
                "user": "U4ZRFG1V0",
                "ts": "1548074277.410100"
            },
            {
                "user": "U4ZRFG1V0",
                "ts": "1548074329.410300"
            },
            {
                "user": "U1CF22N7J",
                "ts": "1548074365.410700"
            },
            {
                "user": "U44J8KC13",
                "ts": "1548074406.411000"
            },
            {
                "user": "U4ZRFG1V0",
                "ts": "1548074925.411300"
            },
            {
                "user": "U6XP4JL49",
                "ts": "1548075263.411800"
            },
            {
                "user": "U35B82XT6",
                "ts": "1548075572.416200"
            },
            {
                "user": "U48SBCYKX",
                "ts": "1548077542.417100"
            },
            {
                "user": "U4ZRFG1V0",
                "ts": "1548077655.417300"
            },
            {
                "user": "U35B82XT6",
                "ts": "1548078122.418200"
            },
            {
                "user": "U48SBCYKX",
                "ts": "1548078223.420700"
            },
            {
                "user": "U48SBCYKX",
                "ts": "1548078335.423500"
            },
            {
                "user": "U4ZRFG1V0",
                "ts": "1548078359.424000"
            },
            {
                "user": "U35B82XT6",
                "ts": "1548078398.424700"
            },
            {
                "user": "U48SBCYKX",
                "ts": "1548078503.424900"
            },
            {
                "user": "U35B82XT6",
                "ts": "1548078610.426700"
            },
            {
                "user": "U48SBCYKX",
                "ts": "1548078828.426900"
            },
            {
                "user": "U0H8RU34N",
                "ts": "1548078889.427100"
            },
            {
                "user": "U48SBCYKX",
                "ts": "1548078957.427400"
            },
            {
                "user": "U4ZRFG1V0",
                "ts": "1548078968.427700"
            },
            {
                "user": "U0H8RU34N",
                "ts": "1548079126.428000"
            },
            {
                "user": "U4ZRFG1V0",
                "ts": "1548079772.436800"
            },
            {
                "user": "U48SBCYKX",
                "ts": "1548080323.441900"
            },
            {
                "user": "U48SBCYKX",
                "ts": "1548082776.446700"
            },
            {
                "user": "U0H8RU34N",
                "ts": "1548083320.447300"
            },
            {
                "user": "U0H8RU34N",
                "ts": "1548083364.447700"
            },
            {
                "user": "U0H8RU34N",
                "ts": "1548083712.448200"
            },
            {
                "user": "U4ZRFG1V0",
                "ts": "1548083782.448400"
            },
            {
                "user": "U48SBCYKX",
                "ts": "1548084676.449400"
            },
            {
                "user": "UDTFQJN1M",
                "ts": "1548135051.461400"
            },
            {
                "user": "UA74839JP",
                "ts": "1548763957.634700"
            }
        ],
        "subscribed": false,
        "reactions": [
            {
                "name": "kaggle",
                "users": [
                    "U0DA4J82H"
                ],
                "count": 1
            }
        ]
    },
    {
        "client_msg_id": "cce031a9-871b-40c6-9cdb-a000f4043432",
        "type": "message",
        "text": "Интересно какой будет дисперсия ответов. Чуть позже, напишу свою оценку. И если в ответах будут повторяющиеся но “несовместимые” варианты, то сделаю “голосовалку” за даиапазоны.",
        "user": "U48SBCYKX",
        "ts": "1548073947.409600",
        "team": "T040HKJE3",
        "user_team": "T040HKJE3",
        "source_team": "T040HKJE3",
        "user_profile": {
            "avatar_hash": "175d7cc768d0",
            "image_72": "https:\/\/avatars.slack-edge.com\/2017-08-24\/232430990807_175d7cc768d09d76d66a_72.jpg",
            "first_name": "Yury",
            "real_name": "Yury Zelensky",
            "display_name": "y.zelensky",
            "team": "T040HKJE3",
            "name": "y.zelensky",
            "is_restricted": false,
            "is_ultra_restricted": false
        },
        "thread_ts": "1548073817.409300",
        "parent_user_id": "U48SBCYKX"
    },
    {
        "client_msg_id": "c874e74e-e92c-41fc-80b1-1b39cafb2a7e",
        "type": "message",
        "text": "`самостоятельно вести DS\/ML проекты` - это очень сильно зависит от проектов. Есть более-менее стандартные задачи, которые хорошо матчатся на таблички: data &amp; labels -&gt; feature extraction -&gt; selection &amp; filtering -&gt; `cross_val_score(sgboost, x, y, cv=5)`. С картинками есть тоже более-менее стандартные подходы типа переобучения лишь головы сети, обученной на imagenet. TLDR - задача классификации довольно хорошо решается существующими фреймворками - и можно довольно быстро построить pipeline (несколько недель обучения при полном отсутствии опыта), не особо вдаваясь в детали с приемлемым качеством. Имхо",
        "user": "U48B3EN87",
        "ts": "1548074179.409800",
        "team": "T040HKJE3",
        "user_team": "T040HKJE3",
        "source_team": "T040HKJE3",
        "user_profile": {
            "avatar_hash": "3c7a34914705",
            "image_72": "https:\/\/avatars.slack-edge.com\/2018-01-27\/305499298995_3c7a34914705a4753a5a_72.jpg",
            "first_name": "Egor",
            "real_name": "Egor",
            "display_name": "abracadabra",
            "team": "T040HKJE3",
            "name": "abracadabra",
            "is_restricted": false,
            "is_ultra_restricted": false
        },
        "edited": {
            "user": "U48B3EN87",
            "ts": "1548074215.000000"
        },
        "thread_ts": "1548073817.409300",
        "parent_user_id": "U48SBCYKX",
        "reactions": [
            {
                "name": "heavy_plus_sign",
                "users": [
                    "U4ZRFG1V0"
                ],
                "count": 1
            }
        ]
    },
    {
        "client_msg_id": "879adcbe-0d02-4adf-8750-97673b79108d",
        "type": "message",
        "text": "&gt;приносить пользу в команде.\n&gt;самостоятельно вести DS\/ML проекты\nЭто принципиально разные уровни.\n\nНу и всё-таки вопрос в том, что надо. сделать fit-predict - легко. Строить простые пайплайны на стандартные проблемы можно за пару месяцев навостриться.\nДелать это с приличным качеством и пониманием - может быть полгода-год для конкретного направления.",
        "user": "U4ZRFG1V0",
        "ts": "1548074277.410100",
        "team": "T040HKJE3",
        "user_team": "T040HKJE3",
        "source_team": "T040HKJE3",
        "user_profile": {
            "avatar_hash": "6345700e36e2",
            "image_72": "https:\/\/avatars.slack-edge.com\/2018-04-29\/355308316530_6345700e36e2a605f712_72.jpg",
            "first_name": "Andrey",
            "real_name": "Andrey Lukyanenko",
            "display_name": "artgor",
            "team": "T040HKJE3",
            "name": "artgor",
            "is_restricted": false,
            "is_ultra_restricted": false
        },
        "thread_ts": "1548073817.409300",
        "parent_user_id": "U48SBCYKX"
    },
    {
        "client_msg_id": "b3090617-c935-402b-a5e8-94e5d7d36034",
        "type": "message",
        "text": "И я бы сказал, что \"вести проекты\" никакие курсы не учат, для этого практический опыт нужен.",
        "user": "U4ZRFG1V0",
        "ts": "1548074329.410300",
        "team": "T040HKJE3",
        "user_team": "T040HKJE3",
        "source_team": "T040HKJE3",
        "user_profile": {
            "avatar_hash": "6345700e36e2",
            "image_72": "https:\/\/avatars.slack-edge.com\/2018-04-29\/355308316530_6345700e36e2a605f712_72.jpg",
            "first_name": "Andrey",
            "real_name": "Andrey Lukyanenko",
            "display_name": "artgor",
            "team": "T040HKJE3",
            "name": "artgor",
            "is_restricted": false,
            "is_ultra_restricted": false
        },
        "edited": {
            "user": "U4ZRFG1V0",
            "ts": "1548074331.000000"
        },
        "thread_ts": "1548073817.409300",
        "parent_user_id": "U48SBCYKX"
    },
    {
        "client_msg_id": "7c6a92b8-61e3-4740-9484-d7e52a755db7",
        "type": "message",
        "text": "\"а когда сдавать?\"",
        "user": "U1CF22N7J",
        "ts": "1548074365.410700",
        "team": "T040HKJE3",
        "user_team": "T040HKJE3",
        "source_team": "T040HKJE3",
        "user_profile": {
            "avatar_hash": "ed5fe9cb6c5e",
            "image_72": "https:\/\/avatars.slack-edge.com\/2020-08-04\/1266881340567_ed5fe9cb6c5e20efa19b_72.png",
            "first_name": "Random",
            "real_name": "Random Letters",
            "display_name": "cepera_ang",
            "team": "T040HKJE3",
            "name": "cepera_ang",
            "is_restricted": false,
            "is_ultra_restricted": false
        },
        "thread_ts": "1548073817.409300",
        "parent_user_id": "U48SBCYKX",
        "reactions": [
            {
                "name": "povar",
                "users": [
                    "U4ZRFG1V0",
                    "U27SUBTB9",
                    "UF54HNE0H",
                    "U9LKKNJHE",
                    "U4WM1939Q",
                    "U9JG577D1",
                    "UDK41MN5U",
                    "UD37TP39U",
                    "UE259V12B",
                    "U91DVVDT9"
                ],
                "count": 10
            },
            {
                "name": "heavy_plus_sign",
                "users": [
                    "U5H0L5T98"
                ],
                "count": 1
            }
        ]
    },
    {
        "client_msg_id": "90ae85d6-876e-4ff9-ba60-cd555a0cd64f",
        "type": "message",
        "text": "во-первых, слишком разные области - от фронтендеров которые тоже считаются программистами до программистов контроллеров. но в целом если прям среднее - думаю в районе 3-6 месяцев при выделении порядка 2-3 часов в день в рабочие дни вне дедлайнов... так что в целом получается что-то около 180 - 360 часов",
        "user": "U44J8KC13",
        "ts": "1548074406.411000",
        "team": "T040HKJE3",
        "user_team": "T040HKJE3",
        "source_team": "T040HKJE3",
        "user_profile": {
            "avatar_hash": "ee63abe6fa1a",
            "image_72": "https:\/\/avatars.slack-edge.com\/2017-03-08\/150900557329_ee63abe6fa1a64bfe7b4_72.png",
            "first_name": "Dmitry",
            "real_name": "Dmitry Selunin",
            "display_name": "aideveloper",
            "team": "T040HKJE3",
            "name": "aideveloper",
            "is_restricted": false,
            "is_ultra_restricted": false
        },
        "thread_ts": "1548073817.409300",
        "parent_user_id": "U48SBCYKX"
    },
    {
        "client_msg_id": "da8cd0cf-d957-4770-93ac-8387e5ff6e96",
        "type": "message",
        "text": "Без знаний программирования у меня ушло 8 месяцев, чтобы получить первую работу. И потом ещё до фига времени на работах, чтобы достичь хоть сколько-то приличный уровень",
        "user": "U4ZRFG1V0",
        "ts": "1548074925.411300",
        "team": "T040HKJE3",
        "user_team": "T040HKJE3",
        "source_team": "T040HKJE3",
        "user_profile": {
            "avatar_hash": "6345700e36e2",
            "image_72": "https:\/\/avatars.slack-edge.com\/2018-04-29\/355308316530_6345700e36e2a605f712_72.jpg",
            "first_name": "Andrey",
            "real_name": "Andrey Lukyanenko",
            "display_name": "artgor",
            "team": "T040HKJE3",
            "name": "artgor",
            "is_restricted": false,
            "is_ultra_restricted": false
        },
        "thread_ts": "1548073817.409300",
        "parent_user_id": "U48SBCYKX"
    },
    {
        "client_msg_id": "78f85c81-d435-4b37-b70c-307230223fa0",
        "type": "message",
        "text": "Спрашивают у студента 1-го курса:\n— За сколько времени можно выучить китайский язык?\nОн подумал и говорит:\n— Ну примерно за год.\nСпрашивают у студента 2-го курса:\n— За сколько времени можно выучить китайский язык?\nОн подумал и говорит:\n— Ну примерно за семестр.\n... и так далее ...\nСпрашивают у студента 5-го курса:\n— За сколько времени можно выучить китайский язык?\nОн в ответ:\n— Методичка есть?\nЕму отвечают:\n— Да, конечно.\nОн:\n— Тогда ща докурим — пойдем сдавать.",
        "user": "U6XP4JL49",
        "ts": "1548075263.411800",
        "team": "T040HKJE3",
        "user_team": "T040HKJE3",
        "source_team": "T040HKJE3",
        "user_profile": {
            "avatar_hash": "6558858ca619",
            "image_72": "https:\/\/avatars.slack-edge.com\/2018-08-20\/418586535792_6558858ca6194201f721_72.jpg",
            "first_name": "Григорий",
            "real_name": "Григорий Вашкевич",
            "display_name": "gvashkevich",
            "team": "T040HKJE3",
            "name": "gvashkevich",
            "is_restricted": false,
            "is_ultra_restricted": false
        },
        "thread_ts": "1548073817.409300",
        "parent_user_id": "U48SBCYKX",
        "reactions": [
            {
                "name": "100",
                "users": [
                    "U4ZRFG1V0",
                    "U8H7YKFME",
                    "UBXSJFA4C",
                    "U19EZ8L5D",
                    "UBPJ0RMMX",
                    "U6QCT6YN6",
                    "UA32XBMJ7",
                    "UFSTXBQ7K"
                ],
                "count": 8
            }
        ]
    },
    {
        "client_msg_id": "B4EE094A-1E63-4BFF-B32B-64DE7AFDEF5A",
        "type": "message",
        "text": "Да быстро должно быть - инструментарий практически стандартизованный. Это же не новые подходы\/алгоритмы делать. Все таки стандартный data scientist сейчас это скорее инженер, который использует готовые библиотеки, методы и алгоритмы для создания модели.  ",
        "user": "U35B82XT6",
        "ts": "1548075572.416200",
        "team": "T040HKJE3",
        "user_team": "T040HKJE3",
        "source_team": "T040HKJE3",
        "user_profile": {
            "avatar_hash": "g53296a021e3",
            "image_72": "https:\/\/secure.gravatar.com\/avatar\/e853296a021e378c6fbdeac90551214a.jpg?s=72&d=https%3A%2F%2Fa.slack-edge.com%2Fdf10d%2Fimg%2Favatars%2Fava_0024-72.png",
            "first_name": "Roman",
            "real_name": "Roman",
            "display_name": "romann",
            "team": "T040HKJE3",
            "name": "romann",
            "is_restricted": false,
            "is_ultra_restricted": false
        },
        "thread_ts": "1548073817.409300",
        "parent_user_id": "U48SBCYKX"
    },
    {
        "client_msg_id": "f8af84da-dee8-40c7-b7b4-a6580a3ecacd",
        "type": "message",
        "text": "так как в основном ответы в duration  (который тоже важен, и после определенного предела интенсификации, эффективность будет падать) уточню, что интересно было бы получить оценку именно в часах - efforts.\n\n Вот например для изучения английского языка на уровне достаточном для профессионального общения (но не на уровне “носителя“) по разным оценкам требуется от 600 до 1200 часов. Тут имеется ввиду в сумме и ассистируемое изучение, и самостоятельная работа.",
        "user": "U48SBCYKX",
        "ts": "1548077542.417100",
        "team": "T040HKJE3",
        "user_team": "T040HKJE3",
        "source_team": "T040HKJE3",
        "user_profile": {
            "avatar_hash": "175d7cc768d0",
            "image_72": "https:\/\/avatars.slack-edge.com\/2017-08-24\/232430990807_175d7cc768d09d76d66a_72.jpg",
            "first_name": "Yury",
            "real_name": "Yury Zelensky",
            "display_name": "y.zelensky",
            "team": "T040HKJE3",
            "name": "y.zelensky",
            "is_restricted": false,
            "is_ultra_restricted": false
        },
        "thread_ts": "1548073817.409300",
        "parent_user_id": "U48SBCYKX"
    },
    {
        "client_msg_id": "8cec6727-ae2d-4e4f-9b04-4eccca697deb",
        "type": "message",
        "text": "опять же, надо различать умение.\nМожно научиться вытаскивать данные из базы и делать fit-predict в пределах рабочей недели (40 часов), но что это даст?\n\nВообще ещё лично я считаю, что DS должен не только уметь кодить, но и думать, анализировать, общаться с заказчиками. Это значительно сложнее.",
        "user": "U4ZRFG1V0",
        "ts": "1548077655.417300",
        "team": "T040HKJE3",
        "user_team": "T040HKJE3",
        "source_team": "T040HKJE3",
        "user_profile": {
            "avatar_hash": "6345700e36e2",
            "image_72": "https:\/\/avatars.slack-edge.com\/2018-04-29\/355308316530_6345700e36e2a605f712_72.jpg",
            "first_name": "Andrey",
            "real_name": "Andrey Lukyanenko",
            "display_name": "artgor",
            "team": "T040HKJE3",
            "name": "artgor",
            "is_restricted": false,
            "is_ultra_restricted": false
        },
        "thread_ts": "1548073817.409300",
        "parent_user_id": "U48SBCYKX",
        "reactions": [
            {
                "name": "heavy_plus_sign",
                "users": [
                    "U15UZGX9A",
                    "U93PQJE1G"
                ],
                "count": 2
            }
        ]
    },
    {
        "client_msg_id": "4466565A-F350-4F2B-A5EE-97475170986D",
        "type": "message",
        "text": "Все это входит в определение инженера",
        "user": "U35B82XT6",
        "ts": "1548078122.418200",
        "team": "T040HKJE3",
        "user_team": "T040HKJE3",
        "source_team": "T040HKJE3",
        "user_profile": {
            "avatar_hash": "g53296a021e3",
            "image_72": "https:\/\/secure.gravatar.com\/avatar\/e853296a021e378c6fbdeac90551214a.jpg?s=72&d=https%3A%2F%2Fa.slack-edge.com%2Fdf10d%2Fimg%2Favatars%2Fava_0024-72.png",
            "first_name": "Roman",
            "real_name": "Roman",
            "display_name": "romann",
            "team": "T040HKJE3",
            "name": "romann",
            "is_restricted": false,
            "is_ultra_restricted": false
        },
        "thread_ts": "1548073817.409300",
        "parent_user_id": "U48SBCYKX"
    },
    {
        "client_msg_id": "62bf5465-988c-4b4b-9b07-456289d1b654",
        "type": "message",
        "text": "Неопределенность заложенную в вопрос, я осознаю. Спасибо всем кто пытается описать её более явно приводя примеры. Но все-же интересно, было бы увидеть конкретную оценку, можете описать свои assumptions. Можете нсеколько оценок для разных assumptions привести. Идея, в том, что как в ансамбле слабых моделей - усреднение даст какую-то разумную картину.",
        "user": "U48SBCYKX",
        "ts": "1548078223.420700",
        "team": "T040HKJE3",
        "user_team": "T040HKJE3",
        "source_team": "T040HKJE3",
        "user_profile": {
            "avatar_hash": "175d7cc768d0",
            "image_72": "https:\/\/avatars.slack-edge.com\/2017-08-24\/232430990807_175d7cc768d09d76d66a_72.jpg",
            "first_name": "Yury",
            "real_name": "Yury Zelensky",
            "display_name": "y.zelensky",
            "team": "T040HKJE3",
            "name": "y.zelensky",
            "is_restricted": false,
            "is_ultra_restricted": false
        },
        "thread_ts": "1548073817.409300",
        "parent_user_id": "U48SBCYKX"
    },
    {
        "client_msg_id": "527a3814-12a7-4c38-ab7b-67a9fa1b345b",
        "type": "message",
        "text": "<@U4ZRFG1V0>, бездумное, механистичское применение единичных методов - безусловно не подпадает ни под какое определение “овладеть методами“.",
        "user": "U48SBCYKX",
        "ts": "1548078335.423500",
        "team": "T040HKJE3",
        "user_team": "T040HKJE3",
        "source_team": "T040HKJE3",
        "user_profile": {
            "avatar_hash": "175d7cc768d0",
            "image_72": "https:\/\/avatars.slack-edge.com\/2017-08-24\/232430990807_175d7cc768d09d76d66a_72.jpg",
            "first_name": "Yury",
            "real_name": "Yury Zelensky",
            "display_name": "y.zelensky",
            "team": "T040HKJE3",
            "name": "y.zelensky",
            "is_restricted": false,
            "is_ultra_restricted": false
        },
        "thread_ts": "1548073817.409300",
        "parent_user_id": "U48SBCYKX"
    },
    {
        "client_msg_id": "c95823c8-9553-4b05-b4af-5de6cddd2df5",
        "type": "message",
        "text": "Попробую тогда взять в пример <http:\/\/mlcourse.ai|mlcourse.ai>\nЭто курс примерно на 2.5 месяца. Для качественного прохождения нужно, наверное, часов 8-10 в неделю - 80-100 часов в сумме (оптимистично, скорее больше). Это примерно уровень джуна, если добавить sql. То есть \"приносить пользу в команде\".",
        "user": "U4ZRFG1V0",
        "ts": "1548078359.424000",
        "team": "T040HKJE3",
        "user_team": "T040HKJE3",
        "source_team": "T040HKJE3",
        "user_profile": {
            "avatar_hash": "6345700e36e2",
            "image_72": "https:\/\/avatars.slack-edge.com\/2018-04-29\/355308316530_6345700e36e2a605f712_72.jpg",
            "first_name": "Andrey",
            "real_name": "Andrey Lukyanenko",
            "display_name": "artgor",
            "team": "T040HKJE3",
            "name": "artgor",
            "is_restricted": false,
            "is_ultra_restricted": false
        },
        "thread_ts": "1548073817.409300",
        "parent_user_id": "U48SBCYKX"
    },
    {
        "client_msg_id": "C22C72B6-BB7D-4F72-AB4E-D1447E7AC77B",
        "type": "message",
        "text": "Вот инженеры, которым ставят  задачу построения 3d модели какого нибудь технологического процесса - они также точно будут анализировать данные, опираться на требования заказчика, использовать им доступный инструментарий в том же Ansys’е с тем, чтобы выдать готовую модель. Потом технологи напишут как именно эта модель будет реализована и запустят в производство.",
        "user": "U35B82XT6",
        "ts": "1548078398.424700",
        "team": "T040HKJE3",
        "user_team": "T040HKJE3",
        "source_team": "T040HKJE3",
        "user_profile": {
            "avatar_hash": "g53296a021e3",
            "image_72": "https:\/\/secure.gravatar.com\/avatar\/e853296a021e378c6fbdeac90551214a.jpg?s=72&d=https%3A%2F%2Fa.slack-edge.com%2Fdf10d%2Fimg%2Favatars%2Fava_0024-72.png",
            "first_name": "Roman",
            "real_name": "Roman",
            "display_name": "romann",
            "team": "T040HKJE3",
            "name": "romann",
            "is_restricted": false,
            "is_ultra_restricted": false
        },
        "thread_ts": "1548073817.409300",
        "parent_user_id": "U48SBCYKX"
    },
    {
        "client_msg_id": "85dba8f1-6ebe-4a2f-ad00-bf20a3b88923",
        "type": "message",
        "text": "моя оценка это 800 часов +-400. разбежка обусловлена и неизбежной разницей в “предрасположенности” (одаренности, если угодно) обучающегося, и эффективностью подбора программы обучения (запросто, можно “забрести не туда“)",
        "user": "U48SBCYKX",
        "ts": "1548078503.424900",
        "team": "T040HKJE3",
        "user_team": "T040HKJE3",
        "source_team": "T040HKJE3",
        "user_profile": {
            "avatar_hash": "175d7cc768d0",
            "image_72": "https:\/\/avatars.slack-edge.com\/2017-08-24\/232430990807_175d7cc768d09d76d66a_72.jpg",
            "first_name": "Yury",
            "real_name": "Yury Zelensky",
            "display_name": "y.zelensky",
            "team": "T040HKJE3",
            "name": "y.zelensky",
            "is_restricted": false,
            "is_ultra_restricted": false
        },
        "thread_ts": "1548073817.409300",
        "parent_user_id": "U48SBCYKX"
    },
    {
        "client_msg_id": "9D15683E-34DE-40C3-A9BC-2AE2A2602CA0",
        "type": "message",
        "text": "По времени все зависит от того, насколько давно изучалась математика. Если человек помнит что такое линейная регрессия то 2-3 месяца это реально, согласен",
        "user": "U35B82XT6",
        "ts": "1548078610.426700",
        "team": "T040HKJE3",
        "user_team": "T040HKJE3",
        "source_team": "T040HKJE3",
        "user_profile": {
            "avatar_hash": "g53296a021e3",
            "image_72": "https:\/\/secure.gravatar.com\/avatar\/e853296a021e378c6fbdeac90551214a.jpg?s=72&d=https%3A%2F%2Fa.slack-edge.com%2Fdf10d%2Fimg%2Favatars%2Fava_0024-72.png",
            "first_name": "Roman",
            "real_name": "Roman",
            "display_name": "romann",
            "team": "T040HKJE3",
            "name": "romann",
            "is_restricted": false,
            "is_ultra_restricted": false
        },
        "thread_ts": "1548073817.409300",
        "parent_user_id": "U48SBCYKX"
    },
    {
        "client_msg_id": "8d9e3d35-1caf-4d5b-95b7-1ff6d90830f8",
        "type": "message",
        "text": "<http:\/\/mlcourse.ai|mlcourse.ai> отличный пример. Но мне кажется 100 часов это ультра оптимистичная оценка (я не спорю, а просто свою оценку даю). Мне кажется для совсем новичка в теме, которму нужно сформировать интуицю по фундаментальным понятиям: регрессия, классификация, ошибка, модель. Да если ещё и без python, например. Понадобится, оптимистично часов 300 ( по 30 часов на тему, включая практику, что хорошо соотносится и с рекомендациями <http:\/\/fast.ai|fast.ai>, например), и это при том, что тут тема сетей даже не затронута.",
        "user": "U48SBCYKX",
        "ts": "1548078828.426900",
        "team": "T040HKJE3",
        "user_team": "T040HKJE3",
        "source_team": "T040HKJE3",
        "user_profile": {
            "avatar_hash": "175d7cc768d0",
            "image_72": "https:\/\/avatars.slack-edge.com\/2017-08-24\/232430990807_175d7cc768d09d76d66a_72.jpg",
            "first_name": "Yury",
            "real_name": "Yury Zelensky",
            "display_name": "y.zelensky",
            "team": "T040HKJE3",
            "name": "y.zelensky",
            "is_restricted": false,
            "is_ultra_restricted": false
        },
        "edited": {
            "user": "U48SBCYKX",
            "ts": "1548079055.000000"
        },
        "thread_ts": "1548073817.409300",
        "parent_user_id": "U48SBCYKX",
        "reactions": [
            {
                "name": "heavy_plus_sign",
                "users": [
                    "U4ZRFG1V0"
                ],
                "count": 1
            }
        ]
    },
    {
        "client_msg_id": "2fdf11de-6e46-4965-9be6-bbb79e5cf5ad",
        "type": "message",
        "text": "Вообще все эти оценки в часах это не совсем то что нужно, скорее это оценка в месяцах, и т ут дело пахнет от года и больше. Это все не только прослушать курс, а еще и попробовать, руками покрутить, позапускать.",
        "user": "U0H8RU34N",
        "ts": "1548078889.427100",
        "team": "T040HKJE3",
        "user_team": "T040HKJE3",
        "source_team": "T040HKJE3",
        "user_profile": {
            "avatar_hash": "85836cba58b8",
            "image_72": "https:\/\/avatars.slack-edge.com\/2015-12-26\/17404364916_85836cba58b8ec1221df_72.jpg",
            "first_name": "Andrey",
            "real_name": "Andrey Lange",
            "display_name": "lange_am",
            "team": "T040HKJE3",
            "name": "lange_am",
            "is_restricted": false,
            "is_ultra_restricted": false
        },
        "edited": {
            "user": "U0H8RU34N",
            "ts": "1548078963.000000"
        },
        "thread_ts": "1548073817.409300",
        "parent_user_id": "U48SBCYKX"
    },
    {
        "client_msg_id": "a3cf392c-2a11-453a-bccb-2365df94c5f8",
        "type": "message",
        "text": "А почему в часах не то? Вот время на английский оценивают в часах, и кореллирует с результатом намного сильнее чем календарные сроки изучения.",
        "user": "U48SBCYKX",
        "ts": "1548078957.427400",
        "team": "T040HKJE3",
        "user_team": "T040HKJE3",
        "source_team": "T040HKJE3",
        "user_profile": {
            "avatar_hash": "175d7cc768d0",
            "image_72": "https:\/\/avatars.slack-edge.com\/2017-08-24\/232430990807_175d7cc768d09d76d66a_72.jpg",
            "first_name": "Yury",
            "real_name": "Yury Zelensky",
            "display_name": "y.zelensky",
            "team": "T040HKJE3",
            "name": "y.zelensky",
            "is_restricted": false,
            "is_ultra_restricted": false
        },
        "thread_ts": "1548073817.409300",
        "parent_user_id": "U48SBCYKX"
    },
    {
        "client_msg_id": "f1866dee-ce15-49bd-b306-8079983f52cf",
        "type": "message",
        "text": "&gt;тема сетей даже не затронута.\nЭто вообще отдельная тема. Имхо, либо человек вкатывается в более классический ML, либо в DL.",
        "user": "U4ZRFG1V0",
        "ts": "1548078968.427700",
        "team": "T040HKJE3",
        "user_team": "T040HKJE3",
        "source_team": "T040HKJE3",
        "user_profile": {
            "avatar_hash": "6345700e36e2",
            "image_72": "https:\/\/avatars.slack-edge.com\/2018-04-29\/355308316530_6345700e36e2a605f712_72.jpg",
            "first_name": "Andrey",
            "real_name": "Andrey Lukyanenko",
            "display_name": "artgor",
            "team": "T040HKJE3",
            "name": "artgor",
            "is_restricted": false,
            "is_ultra_restricted": false
        },
        "thread_ts": "1548073817.409300",
        "parent_user_id": "U48SBCYKX"
    },
    {
        "client_msg_id": "be0cd4cb-3031-465d-b7c2-1593dc33445d",
        "type": "message",
        "text": "Я не верю в изучение английского по занятиям в классе. Хочешь научиться делать дело X - делай дело X. Говорить по английски - просто говории как можно больше, за пару лет начнешь что-то представлять из себя. писать статьи на английском - пиши, и с 1й же статьи уровень будет выше чем был.",
        "user": "U0H8RU34N",
        "ts": "1548079126.428000",
        "team": "T040HKJE3",
        "user_team": "T040HKJE3",
        "source_team": "T040HKJE3",
        "user_profile": {
            "avatar_hash": "85836cba58b8",
            "image_72": "https:\/\/avatars.slack-edge.com\/2015-12-26\/17404364916_85836cba58b8ec1221df_72.jpg",
            "first_name": "Andrey",
            "real_name": "Andrey Lange",
            "display_name": "lange_am",
            "team": "T040HKJE3",
            "name": "lange_am",
            "is_restricted": false,
            "is_ultra_restricted": false
        },
        "thread_ts": "1548073817.409300",
        "parent_user_id": "U48SBCYKX",
        "reactions": [
            {
                "name": "heavy_plus_sign",
                "users": [
                    "UE259V12B",
                    "U8X231ZA6"
                ],
                "count": 2
            }
        ]
    },
    {
        "client_msg_id": "99556dd7-745b-45fd-922d-6b3b6263d499",
        "type": "message",
        "text": "Вот да, в карьере и не только много раз обсуждали, все говорят, что курсов недостаточно, необходима практика",
        "user": "U4ZRFG1V0",
        "ts": "1548079772.436800",
        "team": "T040HKJE3",
        "user_team": "T040HKJE3",
        "source_team": "T040HKJE3",
        "user_profile": {
            "avatar_hash": "6345700e36e2",
            "image_72": "https:\/\/avatars.slack-edge.com\/2018-04-29\/355308316530_6345700e36e2a605f712_72.jpg",
            "first_name": "Andrey",
            "real_name": "Andrey Lukyanenko",
            "display_name": "artgor",
            "team": "T040HKJE3",
            "name": "artgor",
            "is_restricted": false,
            "is_ultra_restricted": false
        },
        "thread_ts": "1548073817.409300",
        "parent_user_id": "U48SBCYKX"
    },
    {
        "client_msg_id": "94316089-ba7b-46ff-a22b-3409f674b3d2",
        "type": "message",
        "text": "Был предложен отличный способ конкретизировать вопрос. Сколько, по вашему мнению, требуется времени на то чтобы освоить материал <https:\/\/mlcourse.aiсообразительному|https:\/\/mlcourse.xn--ai-8kcdvlhzjjeahvlxw2n>, мотивированному инженеру программисту, без знания питона, но с промышленным опытом программирования на другом языке (C#, Java, C++, js) с математическим, но подзабытым образованием (т.е. даже формирование (восстановление) интуиции по таким вопросам как “доверительный интервал” или “линейная регресиия” потребует “вникать в вопрос“).\nОсвоить = “уметь самостоятельно воспроизвести и объяснить, большинство приводимых примеров“.\n\nВарианты:\n:one: - не больше 100 часов на все про всё.\n:two: - 100 - 200 часов\n:three: - 200 - 400 часов\n:four: - 400 - 800 часов\n:five: - 800+ часов\n\nДля справки - в календарном году 2000 “рабочих” часов (при 40 часовой рабочей неделе, без учета отпуска)\n\nОтдельный опрос на duration:\n\n:first_quarter_moon_with_face:- можно упрвиться за месяц\n:last_quarter_moon_with_face:- нужно месяца три, не меньше\n:full_moon_with_face: - пол года - минимум\n:new_moon_with_face: - никак не меньше календарного года.",
        "user": "U48SBCYKX",
        "ts": "1548079907.438100",
        "team": "T040HKJE3",
        "user_team": "T040HKJE3",
        "source_team": "T040HKJE3",
        "user_profile": {
            "avatar_hash": "175d7cc768d0",
            "image_72": "https:\/\/avatars.slack-edge.com\/2017-08-24\/232430990807_175d7cc768d09d76d66a_72.jpg",
            "first_name": "Yury",
            "real_name": "Yury Zelensky",
            "display_name": "y.zelensky",
            "team": "T040HKJE3",
            "name": "y.zelensky",
            "is_restricted": false,
            "is_ultra_restricted": false
        },
        "thread_ts": "1548079907.438100",
        "reply_count": 13,
        "reply_users_count": 7,
        "latest_reply": "1548089070.451800",
        "reply_users": [
            "U4ZRFG1V0",
            "U48SBCYKX",
            "UE259V12B",
            "U04EWH882",
            "U0H7VBQQ1",
            "U04ELQZAU",
            "U1UNFRQ1K"
        ],
        "replies": [
            {
                "user": "U4ZRFG1V0",
                "ts": "1548080008.439700"
            },
            {
                "user": "U48SBCYKX",
                "ts": "1548080072.440600"
            },
            {
                "user": "U48SBCYKX",
                "ts": "1548080117.440800"
            },
            {
                "user": "UE259V12B",
                "ts": "1548080381.442200"
            },
            {
                "user": "U48SBCYKX",
                "ts": "1548080886.443100"
            },
            {
                "user": "U4ZRFG1V0",
                "ts": "1548080978.443600"
            },
            {
                "user": "U04EWH882",
                "ts": "1548081112.443800"
            },
            {
                "user": "U0H7VBQQ1",
                "ts": "1548081806.445400"
            },
            {
                "user": "U48SBCYKX",
                "ts": "1548081876.445700"
            },
            {
                "user": "U48SBCYKX",
                "ts": "1548084880.449800"
            },
            {
                "user": "U04ELQZAU",
                "ts": "1548085352.450200"
            },
            {
                "user": "U48SBCYKX",
                "ts": "1548085747.450600"
            },
            {
                "user": "U1UNFRQ1K",
                "ts": "1548089070.451800"
            }
        ],
        "subscribed": false,
        "reactions": [
            {
                "name": "four",
                "users": [
                    "U48SBCYKX",
                    "U1G303UTW",
                    "U6CJNRTJN",
                    "U9V48C738",
                    "U4U4GFDNK",
                    "U91DVVDT9",
                    "UE0G43GRF",
                    "U1ULNASSV",
                    "U17UDV31D",
                    "UCFQNLN4V"
                ],
                "count": 10
            },
            {
                "name": "two",
                "users": [
                    "U93TH9FU0",
                    "U48379U5D",
                    "U4ZRFG1V0",
                    "UDK41MN5U",
                    "U8H7YKFME",
                    "UEV2FLHPW",
                    "UDUBG85P1",
                    "UB4BD0R6W",
                    "U436BP343",
                    "U0H7VBQQ1",
                    "U60EETE7N",
                    "UE61U6DCL",
                    "U1BMURR5G",
                    "U944AS8DR",
                    "U59CPL6ES",
                    "U64HGTLTD",
                    "U1UNFRQ1K",
                    "UCK3XJ1DM",
                    "U5EE7C38B",
                    "U1ZAJ4FC4",
                    "UED8033PA",
                    "U91RDJA81",
                    "UBTLVD0BD",
                    "UBRK4HXQV",
                    "U70P7K1HS",
                    "UASFK8PG9",
                    "UEQGGMNVD"
                ],
                "count": 27
            },
            {
                "name": "first_quarter_moon_with_face",
                "users": [
                    "U48SBCYKX",
                    "UBTLVD0BD",
                    "U7GFT92PN"
                ],
                "count": 3
            },
            {
                "name": "full_moon_with_face",
                "users": [
                    "U48SBCYKX",
                    "U6T115W2E",
                    "U7KDVG6LS",
                    "UFH5UAADQ"
                ],
                "count": 4
            },
            {
                "name": "new_moon_with_face",
                "users": [
                    "U48SBCYKX",
                    "UF54HNE0H",
                    "U5H0L5T98",
                    "U366HHC4A",
                    "U4B8MC0AD",
                    "UASFK8PG9"
                ],
                "count": 6
            },
            {
                "name": "last_quarter_moon_with_face",
                "users": [
                    "UDK41MN5U",
                    "U48379U5D",
                    "UDUBG85P1",
                    "U6QF7NATC",
                    "UB4BD0R6W",
                    "U93P65UQN",
                    "U4SKDV2HF",
                    "U0H7VBQQ1",
                    "U6MD6AVK2",
                    "U60EETE7N",
                    "U8JCZ254Z",
                    "UEZMQGD6G",
                    "U9V48C738",
                    "UCKTJQG9K",
                    "U7QC6KXJP",
                    "U4U4GFDNK",
                    "U64HGTLTD",
                    "U2AB1PMT5",
                    "UFERVPJQP",
                    "U6NT2E2ES",
                    "UATHUN2BE",
                    "U14DWNVNJ",
                    "UFE7B6UBY",
                    "U1ULNASSV",
                    "UBQJYBVPC",
                    "U1ZAJ4FC4",
                    "U5MN8V5T3",
                    "UA74839JP",
                    "UCEGA2CTD",
                    "UEQGGMNVD"
                ],
                "count": 30
            },
            {
                "name": "three",
                "users": [
                    "UF5FJMNEQ",
                    "U93P65UQN",
                    "U4SKDV2HF",
                    "U7KDVG6LS",
                    "U6MD6AVK2",
                    "UCKTJQG9K",
                    "U49MGP9MX",
                    "U27HU84H4"
                ],
                "count": 8
            },
            {
                "name": "one",
                "users": [
                    "UEWF6GGMN",
                    "U90B3UTFY",
                    "U33G91CMV"
                ],
                "count": 3
            },
            {
                "name": "facepalm",
                "users": [
                    "UDTFQJN1M",
                    "UDKECC8AF"
                ],
                "count": 2
            }
        ]
    },
    {
        "client_msg_id": "e9c4a831-e868-4c97-8b88-0f640b21f7ff",
        "type": "message",
        "text": "<@U1UNFRQ1K>",
        "user": "U4ZRFG1V0",
        "ts": "1548080008.439700",
        "team": "T040HKJE3",
        "user_team": "T040HKJE3",
        "source_team": "T040HKJE3",
        "user_profile": {
            "avatar_hash": "6345700e36e2",
            "image_72": "https:\/\/avatars.slack-edge.com\/2018-04-29\/355308316530_6345700e36e2a605f712_72.jpg",
            "first_name": "Andrey",
            "real_name": "Andrey Lukyanenko",
            "display_name": "artgor",
            "team": "T040HKJE3",
            "name": "artgor",
            "is_restricted": false,
            "is_ultra_restricted": false
        },
        "thread_ts": "1548079907.438100",
        "parent_user_id": "U48SBCYKX"
    },
    {
        "client_msg_id": "c6393c88-75c3-405e-a0da-3eafba9b5b80",
        "type": "message",
        "text": "я потом сниму свои reactions, Пока просто поставил чтобы подряд шли. Ну и всякие юмористические, тоже можно добавлять с monkey и т.п. они уже будут идти “следом” и не будут мешать.",
        "user": "U48SBCYKX",
        "ts": "1548080072.440600",
        "team": "T040HKJE3",
        "user_team": "T040HKJE3",
        "source_team": "T040HKJE3",
        "user_profile": {
            "avatar_hash": "175d7cc768d0",
            "image_72": "https:\/\/avatars.slack-edge.com\/2017-08-24\/232430990807_175d7cc768d09d76d66a_72.jpg",
            "first_name": "Yury",
            "real_name": "Yury Zelensky",
            "display_name": "y.zelensky",
            "team": "T040HKJE3",
            "name": "y.zelensky",
            "is_restricted": false,
            "is_ultra_restricted": false
        },
        "thread_ts": "1548079907.438100",
        "parent_user_id": "U48SBCYKX"
    },
    {
        "client_msg_id": "bf663240-13bc-4c16-bcc3-dc9ade47084b",
        "type": "message",
        "text": "Всем участвующим в опросе - спасибо!",
        "user": "U48SBCYKX",
        "ts": "1548080117.440800",
        "team": "T040HKJE3",
        "user_team": "T040HKJE3",
        "source_team": "T040HKJE3",
        "user_profile": {
            "avatar_hash": "175d7cc768d0",
            "image_72": "https:\/\/avatars.slack-edge.com\/2017-08-24\/232430990807_175d7cc768d09d76d66a_72.jpg",
            "first_name": "Yury",
            "real_name": "Yury Zelensky",
            "display_name": "y.zelensky",
            "team": "T040HKJE3",
            "name": "y.zelensky",
            "is_restricted": false,
            "is_ultra_restricted": false
        },
        "thread_ts": "1548079907.438100",
        "parent_user_id": "U48SBCYKX"
    },
    {
        "client_msg_id": "6eee484a-86b3-4d6f-a1b1-35e31dda6dc9",
        "type": "message",
        "text": "<@U0H8RU34N>, безусловно. Но это “обучение на практике” тоже входит во время которое необходимо чтобы научится.\nТут можно философски заметить, что мы продолжаем учится всю жизнь, совершенствуюясь и в том, что как нам казалось бы мы уже умееем (:excel:) но вполне можно провести разумную границу кога мы делаем что то преимущественно для обучения, или уже что то что умеем делаем “for fun or profit”",
        "user": "U48SBCYKX",
        "ts": "1548080323.441900",
        "team": "T040HKJE3",
        "user_team": "T040HKJE3",
        "source_team": "T040HKJE3",
        "user_profile": {
            "avatar_hash": "175d7cc768d0",
            "image_72": "https:\/\/avatars.slack-edge.com\/2017-08-24\/232430990807_175d7cc768d09d76d66a_72.jpg",
            "first_name": "Yury",
            "real_name": "Yury Zelensky",
            "display_name": "y.zelensky",
            "team": "T040HKJE3",
            "name": "y.zelensky",
            "is_restricted": false,
            "is_ultra_restricted": false
        },
        "thread_ts": "1548073817.409300",
        "parent_user_id": "U48SBCYKX"
    },
    {
        "client_msg_id": "3d5161ec-b538-4c57-acf1-05306f6b231f",
        "type": "message",
        "text": "Питон для ДС учится по сути на лету, минимальный базис можно посмотреть на ютубе за несколько часов (базовый pandas, лямбды, базовый numpy, основы и подводные камни ООП).\nНа cs231n есть как раз такой мануал в текстовом виде.",
        "user": "UE259V12B",
        "ts": "1548080381.442200",
        "team": "T040HKJE3",
        "user_team": "T040HKJE3",
        "source_team": "T040HKJE3",
        "user_profile": {
            "avatar_hash": "f4d13dd6b115",
            "image_72": "https:\/\/avatars.slack-edge.com\/2019-02-07\/546167886790_f4d13dd6b11503315e56_72.jpg",
            "first_name": "SergeKK",
            "real_name": "SergeKK",
            "display_name": "SergeKK",
            "team": "T040HKJE3",
            "name": "borkinks",
            "is_restricted": false,
            "is_ultra_restricted": false
        },
        "thread_ts": "1548079907.438100",
        "parent_user_id": "U48SBCYKX"
    },
    {
        "client_msg_id": "e6ab4710-9173-47a6-9bcd-10d75ec458c4",
        "type": "message",
        "text": "Боюсь, что насчет python (как и pandas) за несколько часов, это систематический bias. Вероятно, связанный  с эффектом Данинга-Крюгера (в том смысле, что обладающий знаниями недооценивает их объем).\nВот, например, разумный, самый базовый курс, который при этом рассчитан на 10-20 часов (лекции в перемешку с практикой - два дня)\n<https:\/\/developers.google.com\/edu\/python\/>",
        "user": "U48SBCYKX",
        "ts": "1548080886.443100",
        "team": "T040HKJE3",
        "user_team": "T040HKJE3",
        "source_team": "T040HKJE3",
        "user_profile": {
            "avatar_hash": "175d7cc768d0",
            "image_72": "https:\/\/avatars.slack-edge.com\/2017-08-24\/232430990807_175d7cc768d09d76d66a_72.jpg",
            "first_name": "Yury",
            "real_name": "Yury Zelensky",
            "display_name": "y.zelensky",
            "team": "T040HKJE3",
            "name": "y.zelensky",
            "is_restricted": false,
            "is_ultra_restricted": false
        },
        "attachments": [
            {
                "service_name": "Google Developers",
                "title": "Google's Python Class  |  Python Education        |  Google Developers",
                "title_link": "https:\/\/developers.google.com\/edu\/python\/",
                "text": "Assorted educational materials provided by Google.",
                "fallback": "Google Developers: Google's Python Class  |  Python Education        |  Google Developers",
                "image_url": "https:\/\/developers.google.com\/_static\/d179425f4c\/images\/share\/devsite-cyan.png",
                "image_width": 476,
                "image_height": 250,
                "from_url": "https:\/\/developers.google.com\/edu\/python\/",
                "image_bytes": 62268,
                "service_icon": "https:\/\/developers.google.com\/_static\/d179425f4c\/images\/touch-icon.png",
                "id": 1,
                "original_url": "https:\/\/developers.google.com\/edu\/python\/"
            }
        ],
        "thread_ts": "1548079907.438100",
        "parent_user_id": "U48SBCYKX"
    },
    {
        "client_msg_id": "7abfe853-b0be-47c7-bf15-1f975cb968d2",
        "type": "message",
        "text": "Помнится уже отмечали, что те, кто учит питон шустро, потом нередко в <#C044B7CSQ|lang_python> задают совсем базовые вопросы или вопросы о скорости работы кода, который совсем не эффективен",
        "user": "U4ZRFG1V0",
        "ts": "1548080978.443600",
        "team": "T040HKJE3",
        "user_team": "T040HKJE3",
        "source_team": "T040HKJE3",
        "user_profile": {
            "avatar_hash": "6345700e36e2",
            "image_72": "https:\/\/avatars.slack-edge.com\/2018-04-29\/355308316530_6345700e36e2a605f712_72.jpg",
            "first_name": "Andrey",
            "real_name": "Andrey Lukyanenko",
            "display_name": "artgor",
            "team": "T040HKJE3",
            "name": "artgor",
            "is_restricted": false,
            "is_ultra_restricted": false
        },
        "thread_ts": "1548079907.438100",
        "parent_user_id": "U48SBCYKX",
        "reactions": [
            {
                "name": "+1",
                "users": [
                    "U48SBCYKX"
                ],
                "count": 1
            },
            {
                "name": "heavy_plus_sign",
                "users": [
                    "U6YDWF4UB",
                    "U60EETE7N",
                    "U8M8GELUB"
                ],
                "count": 3
            }
        ]
    },
    {
        "client_msg_id": "ea379585-a57b-4a43-971e-1f2e92c74176",
        "type": "message",
        "text": "что значит\n&gt; объяснить, большинство приводимых примеров\nчто значит объяснить?\n\nобъяснить можно уметь и после 10 часов.\nа какие-то аспекты и интерпретации могут потребовать 800+ часов.",
        "user": "U04EWH882",
        "ts": "1548081112.443800",
        "team": "T040HKJE3",
        "user_team": "T040HKJE3",
        "source_team": "T040HKJE3",
        "user_profile": {
            "avatar_hash": "7bf410f11342",
            "image_72": "https:\/\/avatars.slack-edge.com\/2020-05-12\/1132281472481_7bf410f1134213219a5f_72.png",
            "first_name": "Alexey",
            "real_name": "Alexey",
            "display_name": "zhirzemli",
            "team": "T040HKJE3",
            "name": "alexeykarnachev",
            "is_restricted": false,
            "is_ultra_restricted": false
        },
        "thread_ts": "1548079907.438100",
        "parent_user_id": "U48SBCYKX"
    },
    {
        "client_msg_id": "bf8ef439-f127-48db-ba9d-32da6eb27a40",
        "type": "message",
        "text": "&gt; задают совсем базовые вопросы или вопросы о скорости работы кода, который совсем не эффективен\n\nВсе-таки спрашивает не наглый фрешград, а человек\n`c промышленным опытом программирования на другом языке`.",
        "user": "U0H7VBQQ1",
        "ts": "1548081806.445400",
        "team": "T040HKJE3",
        "user_team": "T040HKJE3",
        "source_team": "T040HKJE3",
        "user_profile": {
            "avatar_hash": "gfbf37783fcc",
            "image_72": "https:\/\/secure.gravatar.com\/avatar\/ecfbf37783fccca869c3f41a4c4dc792.jpg?s=72&d=https%3A%2F%2Fa.slack-edge.com%2Fdf10d%2Fimg%2Favatars%2Fava_0000-72.png",
            "first_name": "Alex",
            "real_name": "Alex Ozerin",
            "display_name": "alex.ozerin",
            "team": "T040HKJE3",
            "name": "alex.ozerin",
            "is_restricted": false,
            "is_ultra_restricted": false
        },
        "edited": {
            "user": "U0H7VBQQ1",
            "ts": "1548081833.000000"
        },
        "thread_ts": "1548079907.438100",
        "parent_user_id": "U48SBCYKX",
        "reactions": [
            {
                "name": "okay",
                "users": [
                    "U4ZRFG1V0",
                    "U9V48C738"
                ],
                "count": 2
            },
            {
                "name": "heavy_plus_sign",
                "users": [
                    "U04ELQZAU"
                ],
                "count": 1
            }
        ]
    },
    {
        "client_msg_id": "a19f3911-63d9-47cd-9778-7de4f4ee05eb",
        "type": "message",
        "text": "имеется ввиду, не заучить код на память, и переписать его из памяти в ноутбук, а иметь хоть какое-то продуктивное представление о том, что именно он делает. “Продуктивное” представление, это такое которое позволило бы приеменить навыкие к решению другой задачи (не той что была в учебном примере).",
        "user": "U48SBCYKX",
        "ts": "1548081876.445700",
        "team": "T040HKJE3",
        "user_team": "T040HKJE3",
        "source_team": "T040HKJE3",
        "user_profile": {
            "avatar_hash": "175d7cc768d0",
            "image_72": "https:\/\/avatars.slack-edge.com\/2017-08-24\/232430990807_175d7cc768d09d76d66a_72.jpg",
            "first_name": "Yury",
            "real_name": "Yury Zelensky",
            "display_name": "y.zelensky",
            "team": "T040HKJE3",
            "name": "y.zelensky",
            "is_restricted": false,
            "is_ultra_restricted": false
        },
        "edited": {
            "user": "U48SBCYKX",
            "ts": "1548081964.000000"
        },
        "thread_ts": "1548079907.438100",
        "parent_user_id": "U48SBCYKX"
    },
    {
        "client_msg_id": "00dae98a-636e-43cf-b111-d5bdffae404a",
        "type": "message",
        "text": "*учиться :slightly_smiling_face:",
        "user": "U48SBCYKX",
        "ts": "1548082776.446700",
        "team": "T040HKJE3",
        "user_team": "T040HKJE3",
        "source_team": "T040HKJE3",
        "user_profile": {
            "avatar_hash": "175d7cc768d0",
            "image_72": "https:\/\/avatars.slack-edge.com\/2017-08-24\/232430990807_175d7cc768d09d76d66a_72.jpg",
            "first_name": "Yury",
            "real_name": "Yury Zelensky",
            "display_name": "y.zelensky",
            "team": "T040HKJE3",
            "name": "y.zelensky",
            "is_restricted": false,
            "is_ultra_restricted": false
        },
        "thread_ts": "1548073817.409300",
        "parent_user_id": "U48SBCYKX"
    },
    {
        "client_msg_id": "d0c1a299-2876-43b3-8055-d74bed09c7b8",
        "type": "message",
        "text": "Просто я был в industry более 11 лет) И эта привычка планировать расходы и время на образование, время на проект, где не просто запилить, а надо данные разгадать, например, выявить нужные фичи, сделать предобработку сигналов, прочесть кучу литературы, еще поднять знаний немного по теории - нехорошая привычка ) Обычно не доводила дело до продакшена вообще. Такие дела, где есть датасет (или его еще надо получить!) и надо построить модель - это больше похоже на академический ресерч, чем на задачу industry. Даже Kaggle, хоть он и решает зачастую нереальные задачи с искусственно захешированными данными и борьба идет за сотые доли, хотя для бизнеса хватило бы и 100го места из лидерборда, но суть в том, ч о это ресерч, т.к. ключевое слово зачастую это РАЗГАДАТЬ, а просто ЗАПИЛИТЬ функционал.",
        "user": "U0H8RU34N",
        "ts": "1548083320.447300",
        "team": "T040HKJE3",
        "user_team": "T040HKJE3",
        "source_team": "T040HKJE3",
        "user_profile": {
            "avatar_hash": "85836cba58b8",
            "image_72": "https:\/\/avatars.slack-edge.com\/2015-12-26\/17404364916_85836cba58b8ec1221df_72.jpg",
            "first_name": "Andrey",
            "real_name": "Andrey Lange",
            "display_name": "lange_am",
            "team": "T040HKJE3",
            "name": "lange_am",
            "is_restricted": false,
            "is_ultra_restricted": false
        },
        "thread_ts": "1548073817.409300",
        "parent_user_id": "U48SBCYKX"
    },
    {
        "client_msg_id": "9d22c45f-373d-4411-a3d3-0393c586fd34",
        "type": "message",
        "text": "Ставить Data Science на конвеер  - это всегда было провально ...)))",
        "user": "U0H8RU34N",
        "ts": "1548083364.447700",
        "team": "T040HKJE3",
        "user_team": "T040HKJE3",
        "source_team": "T040HKJE3",
        "user_profile": {
            "avatar_hash": "85836cba58b8",
            "image_72": "https:\/\/avatars.slack-edge.com\/2015-12-26\/17404364916_85836cba58b8ec1221df_72.jpg",
            "first_name": "Andrey",
            "real_name": "Andrey Lange",
            "display_name": "lange_am",
            "team": "T040HKJE3",
            "name": "lange_am",
            "is_restricted": false,
            "is_ultra_restricted": false
        },
        "thread_ts": "1548073817.409300",
        "parent_user_id": "U48SBCYKX"
    },
    {
        "client_msg_id": "d6187d12-7779-4a3a-a134-d3eec2f4bcd5",
        "type": "message",
        "text": "<@U48SBCYKX> Предлагаю вам не рассматривать это образование как дополнительное время, у которого есть конец, после которого якобы наступит рай. Не наступит. Это процесс, в котором надо начать жить, новый стиль работы, где теперь появилась DS, ML и т.д. Не надо спрашивать себя через сколько времени я похудею или накачаюсь если начну ходить в тренажерный зал. В вашем сознании у этого не должно быть конца, т.к. началась новая жизнь, в которой в вашей привычке появился новый элемент - тренировки, и это на всю жизнь, а результат будет, еме некуда деваться. Я бы просто ввел обязательные курсы для работников (не для всех) и просто спрашивал бы о результах на Coursera например, и отмазаться от этого нельзя. Это новый стиль жизни вашей компании и это навсегда...)))",
        "user": "U0H8RU34N",
        "ts": "1548083712.448200",
        "team": "T040HKJE3",
        "user_team": "T040HKJE3",
        "source_team": "T040HKJE3",
        "user_profile": {
            "avatar_hash": "85836cba58b8",
            "image_72": "https:\/\/avatars.slack-edge.com\/2015-12-26\/17404364916_85836cba58b8ec1221df_72.jpg",
            "first_name": "Andrey",
            "real_name": "Andrey Lange",
            "display_name": "lange_am",
            "team": "T040HKJE3",
            "name": "lange_am",
            "is_restricted": false,
            "is_ultra_restricted": false
        },
        "thread_ts": "1548073817.409300",
        "parent_user_id": "U48SBCYKX",
        "reactions": [
            {
                "name": "true-story",
                "users": [
                    "UENSFU56C"
                ],
                "count": 1
            }
        ]
    },
    {
        "client_msg_id": "3e9b4705-e3ee-4cd5-a54d-a32b97648cb8",
        "type": "message",
        "text": "&gt;Это процесс, в котором надо начать жить, новый стиль работы, где теперь появилась DS, ML и т.д.\n100%. Дальше необходимо продолжать.\n\"Нужно бежать со всех ног, чтобы только оставаться на месте, а чтобы куда-то попасть, надо бежать как минимум вдвое быстрее!\" (Кэррол)",
        "user": "U4ZRFG1V0",
        "ts": "1548083782.448400",
        "team": "T040HKJE3",
        "user_team": "T040HKJE3",
        "source_team": "T040HKJE3",
        "user_profile": {
            "avatar_hash": "6345700e36e2",
            "image_72": "https:\/\/avatars.slack-edge.com\/2018-04-29\/355308316530_6345700e36e2a605f712_72.jpg",
            "first_name": "Andrey",
            "real_name": "Andrey Lukyanenko",
            "display_name": "artgor",
            "team": "T040HKJE3",
            "name": "artgor",
            "is_restricted": false,
            "is_ultra_restricted": false
        },
        "thread_ts": "1548073817.409300",
        "parent_user_id": "U48SBCYKX"
    },
    {
        "client_msg_id": "da8592a9-b2b4-492c-903e-755826bd0db1",
        "type": "message",
        "text": "Я вообще-то, ничего не говорил о целях опроса. И несмотря на то, что я согласен, со всеми идеями по поводу непрерывного обучения, и иными философскими замечаниями. Я, тем не менее, не согласен с тем, что не нужно, или даже вредно, иметь какую-то baseline оценку по “стоимости” наработки тех или иных компетенций. В частности недооценка этой стоимости может сильно вредить планированию (а я считаю, и опрос это ярко подтвердил, что “бытующие” представления, о времени необходимом для освоения базовых навыков\/знаний в сфере ML, существенно смещены в нижнюю сторону, но это и в других сферах так). Я в смежной отрасли (разработка ПО) 20 лет, и я согласен с тем, что иллюзия о том, что все можно запланировать и учесть - скорее вредна. Но сам процесс планирования - безусловно - очень полезен.\nКстати, в том числе у меня был опыт организации именно массового “непрерывного” обучения в компании с 1000+ инженеров. На практике, эффективность, конечно, оказывается гораздо ниже, даже самых пессимистических оценок. И зависимость от личных особенностей обучаемых, и других факторов - выше, чем того бы хотелось. И всё равно, оно (обучение), безусловно, стоит того чтобы в него вкладываться.",
        "user": "U48SBCYKX",
        "ts": "1548084676.449400",
        "team": "T040HKJE3",
        "user_team": "T040HKJE3",
        "source_team": "T040HKJE3",
        "user_profile": {
            "avatar_hash": "175d7cc768d0",
            "image_72": "https:\/\/avatars.slack-edge.com\/2017-08-24\/232430990807_175d7cc768d09d76d66a_72.jpg",
            "first_name": "Yury",
            "real_name": "Yury Zelensky",
            "display_name": "y.zelensky",
            "team": "T040HKJE3",
            "name": "y.zelensky",
            "is_restricted": false,
            "is_ultra_restricted": false
        },
        "thread_ts": "1548073817.409300",
        "parent_user_id": "U48SBCYKX"
    },
    {
        "client_msg_id": "d666d50f-3845-4ae7-836a-f5fdac3b7f1d",
        "type": "message",
        "text": "заметил что ссылка побилась. Имелся ввиду “<http:\/\/mlcourse.ai|mlcourse.ai>”",
        "user": "U48SBCYKX",
        "ts": "1548084880.449800",
        "team": "T040HKJE3",
        "user_team": "T040HKJE3",
        "source_team": "T040HKJE3",
        "user_profile": {
            "avatar_hash": "175d7cc768d0",
            "image_72": "https:\/\/avatars.slack-edge.com\/2017-08-24\/232430990807_175d7cc768d09d76d66a_72.jpg",
            "first_name": "Yury",
            "real_name": "Yury Zelensky",
            "display_name": "y.zelensky",
            "team": "T040HKJE3",
            "name": "y.zelensky",
            "is_restricted": false,
            "is_ultra_restricted": false
        },
        "thread_ts": "1548079907.438100",
        "parent_user_id": "U48SBCYKX"
    },
    {
        "client_msg_id": "f021ef8a-09a4-47d4-a191-bb30567d6e10",
        "type": "message",
        "text": "<@U48SBCYKX>, так курс этот рассчитан на почти совсем новичков, он лишь знание понятия переменной предполагает. Человек, профессионально программировавший на C#, C++ и JS будет в состоянии разобраться в значительной части языка на ходу, а овладеть библиотеками -- вопрос практики и чтения документации",
        "user": "U04ELQZAU",
        "ts": "1548085352.450200",
        "team": "T040HKJE3",
        "user_team": "T040HKJE3",
        "source_team": "T040HKJE3",
        "user_profile": {
            "avatar_hash": "f6bc50fa5754",
            "image_72": "https:\/\/avatars.slack-edge.com\/2016-10-20\/93944572805_f6bc50fa575469918b41_72.png",
            "first_name": "Артём",
            "real_name": "Артём Соболев",
            "display_name": "asobolev",
            "team": "T040HKJE3",
            "name": "asobolev",
            "is_restricted": false,
            "is_ultra_restricted": false
        },
        "thread_ts": "1548079907.438100",
        "parent_user_id": "U48SBCYKX",
        "reactions": [
            {
                "name": "heavy_plus_sign",
                "users": [
                    "UE259V12B",
                    "U17UDV31D"
                ],
                "count": 2
            }
        ]
    },
    {
        "client_msg_id": "fb00633c-d75d-4086-8f88-32759e3093a4",
        "type": "message",
        "text": "под “языком” имеется ввиду, язык изложения материалов курса? Или питон?\nя ни по поводу ни одного ни другого не спорю.\n\nЯ только хочу заметить что, на десятках (правда, не сотнях) примеров, я наблюдал, что те, кто свободно пишут, например, на python, в большинстве случаев, оценивают количество времени которое нужно на то чтобы этим навыком овладеть в единицы часов. Но на практике, фактически, у всех, кто это пытался сделать, в сколь либо контролируемых условиях, на это уходили единицы десятков часов. “По ходу“, конечно, эффективнее. чем на абстактных задачах их решебника, но все-равно это не “само собой“. Не “бесплатно”",
        "user": "U48SBCYKX",
        "ts": "1548085747.450600",
        "team": "T040HKJE3",
        "user_team": "T040HKJE3",
        "source_team": "T040HKJE3",
        "user_profile": {
            "avatar_hash": "175d7cc768d0",
            "image_72": "https:\/\/avatars.slack-edge.com\/2017-08-24\/232430990807_175d7cc768d09d76d66a_72.jpg",
            "first_name": "Yury",
            "real_name": "Yury Zelensky",
            "display_name": "y.zelensky",
            "team": "T040HKJE3",
            "name": "y.zelensky",
            "is_restricted": false,
            "is_ultra_restricted": false
        },
        "thread_ts": "1548079907.438100",
        "parent_user_id": "U48SBCYKX"
    },
    {
        "client_msg_id": "27993cfd-7626-4cf9-8f46-109cb13b7e1f",
        "type": "message",
        "text": "Конечно, все ещё мутно вопрос составлен. Некоторые вещи из курса я сам тоже не объясню :kekeke: \n\nНу допустим. Курс состоит из 10 недель. Если реально ботать по 14 часов в неделю (по 4 на выходных и как-то ещё по 2 часа найти в 3 будних дня) - это дохрена для работающего человека. Но допустим, он ещё сильно мотивирован. То есть всяко получается меньше 200 часов. \n\nА за это время, полагаю, можно освоить базовые вещи, о которых идёт речь в <http:\/\/mlcourse.ai|mlcourse.ai>. Так что :two: ",
        "user": "U1UNFRQ1K",
        "ts": "1548089070.451800",
        "team": "T040HKJE3",
        "user_team": "T040HKJE3",
        "source_team": "T040HKJE3",
        "user_profile": {
            "avatar_hash": "ae220b01b503",
            "image_72": "https:\/\/avatars.slack-edge.com\/2018-06-11\/378543497681_ae220b01b503b2d1bfe8_72.jpg",
            "first_name": "Yury",
            "real_name": "Yury Kashnitsky",
            "display_name": "yorko",
            "team": "T040HKJE3",
            "name": "yorko",
            "is_restricted": false,
            "is_ultra_restricted": false
        },
        "thread_ts": "1548079907.438100",
        "parent_user_id": "U48SBCYKX",
        "reactions": [
            {
                "name": "tnx",
                "users": [
                    "U48SBCYKX"
                ],
                "count": 1
            }
        ]
    },
    {
        "client_msg_id": "b21d600f-1a62-4034-a9a7-850afea70068",
        "type": "message",
        "text": "Добрался до лекций :ng: по DL. Насколько же он круто всё объясняет, какой-то суперталант преподавательский у человека. Ни от чего не наступает такого просветления. Ни от статей с крутыми картинками, ни от видосов на Udacity где всё как для детей на картинках со зверушками объясняется. Покурил вот этот плейлист и просветлился:\n<https:\/\/www.youtube.com\/playlist?list=PL1w8k37X_6L_s4ncq-swTBvKDWnRSrinI>",
        "user": "U60EETE7N",
        "ts": "1548098938.457300",
        "team": "T040HKJE3",
        "user_team": "T040HKJE3",
        "source_team": "T040HKJE3",
        "user_profile": {
            "avatar_hash": "f7e6a648a94b",
            "image_72": "https:\/\/avatars.slack-edge.com\/2019-06-17\/660704542257_f7e6a648a94bf14f6db6_72.jpg",
            "first_name": "sergey",
            "real_name": "sergey zakharov",
            "display_name": "sergei3000",
            "team": "T040HKJE3",
            "name": "sergei3000",
            "is_restricted": false,
            "is_ultra_restricted": false
        },
        "attachments": [
            {
                "service_name": "YouTube",
                "title": "Recurrent Neural Networks | Sequence Models (Course 5 Deep Learning Andrew Ng) - YouTube",
                "title_link": "https:\/\/www.youtube.com\/playlist?list=PL1w8k37X_6L_s4ncq-swTBvKDWnRSrinI",
                "text": "Recurrent Neural Networks (Sequence Models). It is the 5th course of Deep Learning Specialisation by Andrew Ng on Coursera.",
                "fallback": "YouTube: Recurrent Neural Networks | Sequence Models (Course 5 Deep Learning Andrew Ng) - YouTube",
                "thumb_url": "https:\/\/i.ytimg.com\/vi\/efWlOCE_6HY\/hqdefault.jpg?sqp=-oaymwEWCKgBEF5IWvKriqkDCQgBFQAAiEIYAQ==&rs=AOn4CLCiazeE4rgPD2QPSMHmFFkK52gbnA",
                "from_url": "https:\/\/www.youtube.com\/playlist?list=PL1w8k37X_6L_s4ncq-swTBvKDWnRSrinI",
                "thumb_width": 168,
                "thumb_height": 94,
                "service_icon": "https:\/\/s.ytimg.com\/yts\/img\/favicon-vfl8qSV2F.ico",
                "id": 1,
                "original_url": "https:\/\/www.youtube.com\/playlist?list=PL1w8k37X_6L_s4ncq-swTBvKDWnRSrinI"
            }
        ],
        "thread_ts": "1548098938.457300",
        "reply_count": 5,
        "reply_users_count": 4,
        "latest_reply": "1548421447.519900",
        "reply_users": [
            "U6BH6UR0E",
            "UCK3XJ1DM",
            "U60EETE7N",
            "UFLNSF5J5"
        ],
        "replies": [
            {
                "user": "U6BH6UR0E",
                "ts": "1548144100.463400"
            },
            {
                "user": "UCK3XJ1DM",
                "ts": "1548145828.464600"
            },
            {
                "user": "U60EETE7N",
                "ts": "1548146223.464800"
            },
            {
                "user": "U6BH6UR0E",
                "ts": "1548146312.465000"
            },
            {
                "user": "UFLNSF5J5",
                "ts": "1548421447.519900"
            }
        ],
        "subscribed": false,
        "reactions": [
            {
                "name": "heavy_plus_sign",
                "users": [
                    "U5H0L5T98",
                    "U5H055U0J",
                    "U53E5MFNU",
                    "UC3LNBU8L",
                    "UA01WQ4LC",
                    "U8PMZ6397",
                    "UD2NGFPHD",
                    "U4D7EK3N3",
                    "U6R2NHD50",
                    "U0ZJSC8JC",
                    "UD2EX7JP9",
                    "U4ZRFG1V0",
                    "U2VBC4HEX",
                    "U2N853RGF",
                    "U4N7G9RQA",
                    "U59MRBWUS",
                    "U6YT3HHML",
                    "U14DWNVNJ",
                    "UBY1TNNRY",
                    "U6YDWF4UB",
                    "UCK3XJ1DM",
                    "U4M57KTPS",
                    "UAA49DA1W",
                    "U1BMURR5G",
                    "UF2KJ6EF5",
                    "U48SBCYKX",
                    "U17UDV31D",
                    "UFLNSF5J5",
                    "UASFK8PG9",
                    "U6Z21KSBC"
                ],
                "count": 30
            },
            {
                "name": "true-story",
                "users": [
                    "U5H055U0J",
                    "U93S7T13R",
                    "UDHJKLGLR",
                    "UCFQNLN4V",
                    "U0546DHDK"
                ],
                "count": 5
            },
            {
                "name": "muscle",
                "users": [
                    "UAG21HMV4",
                    "U6U41VDQF",
                    "U1D6DT6HE"
                ],
                "count": 3
            },
            {
                "name": "fire",
                "users": [
                    "UDTFQJN1M"
                ],
                "count": 1
            },
            {
                "name": "tnx",
                "users": [
                    "UB4AGRL3C"
                ],
                "count": 1
            },
            {
                "name": "heart_eyes",
                "users": [
                    "UFLNSF5J5",
                    "UASFK8PG9"
                ],
                "count": 2
            }
        ]
    },
    {
        "client_msg_id": "30947226-861e-45e4-8c8f-21a17e555ea2",
        "type": "message",
        "text": "Тут приводят пространные размышления, верные по своей сути конечно же. Ответом на изначальный вопрос ТС является старая добрая цифра в 10 000 часов работы по выбранному направлению. После этого у вас может получиться что-то оригинальное. Этой цифрой оперировал Джобс в своем подходе к найму персонала. Откуда она берется, вкратце здесь <http:\/\/www.forbes.ru\/forbes\/issue\/2009-04\/7255-pravilo-10000-chasov>",
        "user": "UDTFQJN1M",
        "ts": "1548135051.461400",
        "team": "T040HKJE3",
        "user_team": "T040HKJE3",
        "source_team": "T040HKJE3",
        "user_profile": {
            "avatar_hash": "995a69739903",
            "image_72": "https:\/\/avatars.slack-edge.com\/2018-11-01\/469205733107_995a69739903f434986d_72.jpg",
            "first_name": "Igor",
            "real_name": "Igor Popov",
            "display_name": "orsk-moscow",
            "team": "T040HKJE3",
            "name": "igor.v.popov",
            "is_restricted": false,
            "is_ultra_restricted": false
        },
        "edited": {
            "user": "UDTFQJN1M",
            "ts": "1548135068.000000"
        },
        "attachments": [
            {
                "service_name": "Forbes.ru",
                "title": "Правило 10000 часов | Forbes.ru",
                "title_link": "http:\/\/www.forbes.ru\/forbes\/issue\/2009-04\/7255-pravilo-10000-chasov",
                "text": "Откуда берутся выдающиеся достижения",
                "fallback": "Forbes.ru: Правило 10000 часов | Forbes.ru",
                "ts": 1238702400,
                "from_url": "http:\/\/www.forbes.ru\/forbes\/issue\/2009-04\/7255-pravilo-10000-chasov",
                "service_icon": "http:\/\/www.forbes.ru\/themes\/forbes\/img\/favicon.ico",
                "id": 1,
                "original_url": "http:\/\/www.forbes.ru\/forbes\/issue\/2009-04\/7255-pravilo-10000-chasov"
            }
        ],
        "thread_ts": "1548073817.409300",
        "parent_user_id": "U48SBCYKX",
        "reactions": [
            {
                "name": "heavy_minus_sign",
                "users": [
                    "U48SBCYKX"
                ],
                "count": 1
            }
        ]
    }
]