[
    {
        "client_msg_id": "dc89e527-3632-49c6-8870-b4b963ff95b7",
        "type": "message",
        "text": "<https:\/\/www.amazon.com\/Thousand-Exercises-Probability-Geoffrey-Grimmett\/dp\/0198572212|https:\/\/www.amazon.com\/Thousand-Exercises-Probability-Geoffrey-Grimmett\/dp\/0198572212>\nЗдесь есть достаточно хардкорные задачи",
        "user": "U3FEH4R1P",
        "ts": "1574519299.262400",
        "team": "T040HKJE3",
        "user_team": "T040HKJE3",
        "source_team": "T040HKJE3",
        "user_profile": {
            "avatar_hash": "g09e91261943",
            "image_72": "https:\/\/secure.gravatar.com\/avatar\/1809e9126194360100481cb7b0fd71c6.jpg?s=72&d=https%3A%2F%2Fa.slack-edge.com%2Fdf10d%2Fimg%2Favatars%2Fava_0002-72.png",
            "first_name": "Ivan",
            "real_name": "Ivan Lakhtanov",
            "display_name": "vaness",
            "team": "T040HKJE3",
            "name": "vaness",
            "is_restricted": false,
            "is_ultra_restricted": false
        },
        "blocks": [
            {
                "type": "rich_text",
                "block_id": "MPYIr",
                "elements": [
                    {
                        "type": "rich_text_section",
                        "elements": [
                            {
                                "type": "link",
                                "url": "https:\/\/www.amazon.com\/Thousand-Exercises-Probability-Geoffrey-Grimmett\/dp\/0198572212",
                                "text": "https:\/\/www.amazon.com\/Thousand-Exercises-Probability-Geoffrey-Grimmett\/dp\/0198572212"
                            },
                            {
                                "type": "text",
                                "text": "\nЗдесь есть достаточно хардкорные задачи"
                            }
                        ]
                    }
                ]
            }
        ],
        "thread_ts": "1574428949.243100",
        "parent_user_id": "UD17WV276"
    },
    {
        "client_msg_id": "ff1a66b5-02b9-4d57-8cc4-ba91cd190b81",
        "type": "message",
        "text": "В Feller, кажется, были задачи. Достаточно хардкорные",
        "user": "UAVJFD37T",
        "ts": "1574543072.268800",
        "team": "T040HKJE3",
        "user_team": "T040HKJE3",
        "source_team": "T040HKJE3",
        "user_profile": {
            "avatar_hash": "bbb942de8ed7",
            "image_72": "https:\/\/avatars.slack-edge.com\/2018-05-25\/370090565027_bbb942de8ed7eaf3980a_72.jpg",
            "first_name": "Victor",
            "real_name": "Victor Rogulenko",
            "display_name": "rogulenko",
            "team": "T040HKJE3",
            "name": "rogulenko",
            "is_restricted": false,
            "is_ultra_restricted": false
        },
        "blocks": [
            {
                "type": "rich_text",
                "block_id": "iMz",
                "elements": [
                    {
                        "type": "rich_text_section",
                        "elements": [
                            {
                                "type": "text",
                                "text": "В Feller, кажется, были задачи. Достаточно хардкорные"
                            }
                        ]
                    }
                ]
            }
        ],
        "thread_ts": "1574428949.243100",
        "parent_user_id": "UD17WV276"
    },
    {
        "client_msg_id": "b08fb2af-f477-4538-9ca7-39b7ecbce802",
        "type": "message",
        "text": "<@U4WM1939Q> не стоит недооценивать лень народа. Особенно на западе где есть бабло у людей - им сказали заплатить, они заплатили. А письмо заполнять почему беден совесть замучает.\nСамое большое вложение это время, а не 5к рублей в месяц, да и дообучаться обычно хотят работяги у которых уже всё неплохо.\nЯ уверен это :good-enough: решение действительно позволяет курсере собирать деньги с 95%, позволяя 5% условных русских студентов получать курсы бесплатно, расхваливая курсеру на каждом углу\nКак говорится - работает не трогай",
        "user": "UM53RABL7",
        "ts": "1574570329.269100",
        "team": "T040HKJE3",
        "user_team": "T040HKJE3",
        "source_team": "T040HKJE3",
        "user_profile": {
            "avatar_hash": "g8a40d5543cf",
            "image_72": "https:\/\/secure.gravatar.com\/avatar\/c18a40d5543cf444c0ce5ec854699635.jpg?s=72&d=https%3A%2F%2Fa.slack-edge.com%2Fdf10d%2Fimg%2Favatars%2Fava_0012-72.png",
            "first_name": "Vyacheslav",
            "real_name": "Vyacheslav Fokin",
            "display_name": "inslava",
            "team": "T040HKJE3",
            "name": "kdfokin",
            "is_restricted": false,
            "is_ultra_restricted": false
        },
        "blocks": [
            {
                "type": "rich_text",
                "block_id": "RcsWD",
                "elements": [
                    {
                        "type": "rich_text_section",
                        "elements": [
                            {
                                "type": "user",
                                "user_id": "U4WM1939Q"
                            },
                            {
                                "type": "text",
                                "text": " не стоит недооценивать лень народа. Особенно на западе где есть бабло у людей - им сказали заплатить, они заплатили. А письмо заполнять почему беден совесть замучает.\nСамое большое вложение это время, а не 5к рублей в месяц, да и дообучаться обычно хотят работяги у которых уже всё неплохо.\nЯ уверен это "
                            },
                            {
                                "type": "emoji",
                                "name": "good-enough"
                            },
                            {
                                "type": "text",
                                "text": " решение действительно позволяет курсере собирать деньги с 95%, позволяя 5% условных русских студентов получать курсы бесплатно, расхваливая курсеру на каждом углу\nКак говорится - работает не трогай"
                            }
                        ]
                    }
                ]
            }
        ],
        "thread_ts": "1572950729.488000",
        "parent_user_id": "UKT26PF0E"
    },
    {
        "client_msg_id": "de2b20f1-1417-47fc-9330-7739f328abfa",
        "type": "message",
        "text": "На самом деле в чате одного русскоязычного курса встречается \"ой, ребят, у меня деньги кончаются на курс шо делать\" через день\nИ ещё многие признают что платили.\nТак что даже в России многим западло получать годный товар и не платить",
        "user": "UM53RABL7",
        "ts": "1574570457.269300",
        "team": "T040HKJE3",
        "user_team": "T040HKJE3",
        "source_team": "T040HKJE3",
        "user_profile": {
            "avatar_hash": "g8a40d5543cf",
            "image_72": "https:\/\/secure.gravatar.com\/avatar\/c18a40d5543cf444c0ce5ec854699635.jpg?s=72&d=https%3A%2F%2Fa.slack-edge.com%2Fdf10d%2Fimg%2Favatars%2Fava_0012-72.png",
            "first_name": "Vyacheslav",
            "real_name": "Vyacheslav Fokin",
            "display_name": "inslava",
            "team": "T040HKJE3",
            "name": "kdfokin",
            "is_restricted": false,
            "is_ultra_restricted": false
        },
        "blocks": [
            {
                "type": "rich_text",
                "block_id": "lNhv",
                "elements": [
                    {
                        "type": "rich_text_section",
                        "elements": [
                            {
                                "type": "text",
                                "text": "На самом деле в чате одного русскоязычного курса встречается \"ой, ребят, у меня деньги кончаются на курс шо делать\" через день\nИ ещё многие признают что платили.\nТак что даже в России многим западло получать годный товар и не платить"
                            }
                        ]
                    }
                ]
            }
        ],
        "thread_ts": "1572950729.488000",
        "parent_user_id": "UKT26PF0E"
    }
]